pycreate/__init__.py
pycreate/_version.py
pycreate/pip.sh
pycreate/pycreate.py
pycreate/setup.txt
pycreate/setup_conf.txt
fzpycreate-2.0.0.dist-info/LICENSE.md
fzpycreate-2.0.0.dist-info/METADATA
fzpycreate-2.0.0.dist-info/WHEEL
fzpycreate-2.0.0.dist-info/entry_points.txt
fzpycreate-2.0.0.dist-info/top_level.txt
fzpycreate-2.0.0.dist-info/RECORD
