Metadata-Version: 2.1
Name: fzpycreate
Version: 2.0.0
Summary: pycreate
Home-page: UNKNOWN
Author: fanzhao1986
Author-email: fanzhao1986@gmail.com
License: UNKNOWN
Keywords: pycreate
Platform: any
Classifier: Development Status :: 5 - Production/Stable
Classifier: Intended Audience :: Developers
Classifier: License :: OSI Approved :: GNU General Public License v2 (GPLv2)
Classifier: Operating System :: POSIX :: Linux
Classifier: Programming Language :: Python
Classifier: Programming Language :: Python :: 3.7
Classifier: Programming Language :: Python :: 3.8
Classifier: Topic :: Utilities
Requires-Python: >=3.7
Requires-Dist: filelock (==3.0.10)
Requires-Dist: flake8 (==3.6.0)
Requires-Dist: mccabe (==0.6.1)
Requires-Dist: nose (==1.3.7)
Requires-Dist: pluggy (==0.8.1)
Requires-Dist: py (==1.7.0)
Requires-Dist: pycodestyle (==2.4.0)
Requires-Dist: pyflakes (==2.0.0)
Requires-Dist: six (==1.12.0)
Requires-Dist: toml (==0.10.0)
Requires-Dist: tox (==3.5.3)
Requires-Dist: virtualenv (==16.2.0)
